MANIFEST.in
Makefile
README.txt
__init__.py
camera.py
common.py
cvwrap.py
dummy.py
everything.py
filters.py
filtersnew.py
geometry.py
lighting.py
nasa_earth.jpg
nasa_earth.mtl
nasa_earth.obj
occlusion_test.py
renderer.py
serialization.py
setup.py
setup_new.py
simple.py
slider_demo.py
test_camera.py
test_depth_renderer.py
test_geometry.py
test_renderer.py
test_sh.py
topology.py
util_tests.py
utils.py
version.py
./__init__.py
./camera.py
./common.py
./cvwrap.py
./dummy.py
./everything.py
./filters.py
./filtersnew.py
./geometry.py
./lighting.py
./occlusion_test.py
./renderer.py
./serialization.py
./setup_new.py
./simple.py
./slider_demo.py
./test_camera.py
./test_depth_renderer.py
./test_geometry.py
./test_renderer.py
./test_sh.py
./topology.py
./util_tests.py
./utils.py
./version.py
./contexts/__init__.py
./contexts/_constants.py
./contexts/autogen.py
./contexts/draw_triangle_shaders_2_1.py
./contexts/draw_triangle_shaders_3_2.py
./contexts/fix_warnings.py
./test_dr/__init__.py
contexts/Makefile
contexts/__init__.py
contexts/_constants.py
contexts/_functions.pyx
contexts/autogen.py
contexts/ctx_base.pyx
contexts/ctx_mac.c
contexts/ctx_mac.pyx
contexts/ctx_mac_internal.c
contexts/ctx_mac_internal.h
contexts/ctx_mesa.pyx
contexts/draw_triangle_shaders_2_1.py
contexts/draw_triangle_shaders_3_2.py
contexts/fix_warnings.py
contexts/gl_includes.h
contexts/__MACOSX/OSMesa/include/GL/._GLwDrawA.h
contexts/__MACOSX/OSMesa/include/GL/._GLwDrawAP.h
contexts/__MACOSX/OSMesa/include/GL/._GLwMDrawA.h
contexts/__MACOSX/OSMesa/include/GL/._GLwMDrawAP.h
contexts/__MACOSX/OSMesa/include/GL/._gl.h
contexts/__MACOSX/OSMesa/include/GL/._gl_mangle.h
contexts/__MACOSX/OSMesa/include/GL/._glext.h
contexts/__MACOSX/OSMesa/include/GL/._glfbdev.h
contexts/__MACOSX/OSMesa/include/GL/._glu.h
contexts/__MACOSX/OSMesa/include/GL/._glu_mangle.h
contexts/__MACOSX/OSMesa/include/GL/._glut.h
contexts/__MACOSX/OSMesa/include/GL/._glutf90.h
contexts/__MACOSX/OSMesa/include/GL/._glx.h
opendr.egg-info/PKG-INFO
opendr.egg-info/SOURCES.txt
opendr.egg-info/dependency_links.txt
opendr.egg-info/requires.txt
opendr.egg-info/top_level.txt
